README.md
setup.py
MLVisualisation/__init__.py
MLVisualisation/layouts/GridLayout.py
MLVisualisation/layouts/__init__.py
MLVisualisation/plots/BasicPlot.py
MLVisualisation/plots/ConfusionMatrixPlot.py
MLVisualisation/plots/LinePlot.py
MLVisualisation/plots/LossValidationPlot.py
MLVisualisation/plots/PCAPlot.py
MLVisualisation/plots/__init__.py
MLVisualization.egg-info/PKG-INFO
MLVisualization.egg-info/SOURCES.txt
MLVisualization.egg-info/dependency_links.txt
MLVisualization.egg-info/requires.txt
MLVisualization.egg-info/top_level.txt